airtolphin/__init__.py
airtolphin/core/__init__.py
airtolphin/core/transformer.py
airtolphin/rules/__init__.py
airtolphin/rules/dag_context.py
airtolphin/rules/import_from.py
airtolphin/rules/operators.py
airtolphin-0.0.1.dist-info/LICENSE
airtolphin-0.0.1.dist-info/METADATA
airtolphin-0.0.1.dist-info/WHEEL
airtolphin-0.0.1.dist-info/top_level.txt
airtolphin-0.0.1.dist-info/RECORD
