Metadata-Version: 2.1
Name: airtolphin
Version: 0.0.1
Summary: Airflow to DolphinScheduler migration tool
Home-page: https://github.com/WhaleOps/airtolphin
Author: Jay Chung
Author-email: zhongjiajie955@gmail.com
License: Apache License 2.0
Project-URL: Source, https://github.com/WhaleOps/airtolphin
Project-URL: Issue Tracker, https://github.com/WhaleOps/airtolphin/issues
Keywords: transfer,tool,parser,airflow,dolphinscheduler
Platform: any
Classifier: Development Status :: 1 - Planning
Classifier: Environment :: Console
Classifier: Intended Audience :: Developers
Classifier: License :: OSI Approved :: MIT License
Classifier: Operating System :: Unix
Classifier: Operating System :: POSIX
Classifier: Operating System :: MacOS
Classifier: Operating System :: Microsoft :: Windows
Classifier: Programming Language :: Python
Classifier: Programming Language :: Python :: 3.7
Classifier: Programming Language :: Python :: 3.8
Classifier: Programming Language :: Python :: 3.9
Classifier: Programming Language :: Python :: 3.10
Classifier: Programming Language :: Python :: 3.11
Classifier: Programming Language :: Python :: Implementation :: CPython
Classifier: Topic :: Utilities
Classifier: Topic :: Software Development :: Quality Assurance
Requires-Python: >=3.6
License-File: LICENSE
Requires-Dist: libcst
Provides-Extra: dev
Requires-Dist: flake8 (>=4.0) ; extra == 'dev'
Requires-Dist: flake8-docstrings (>=1.6) ; extra == 'dev'
Requires-Dist: flake8-black (>=0.2) ; extra == 'dev'
Requires-Dist: isort (>=5.10) ; extra == 'dev'
Requires-Dist: autoflake (>=1.4) ; extra == 'dev'
